tortik/__init__.py
tortik/logger.py
tortik/page.py
tortik/version.py
tortik/templates/debug.html
tortik/templates/dumper.html
tortik/util/__init__.py
tortik/util/async_group.py
tortik/util/dumper.py
tortik/util/parse.py
tortik/util/url.py
tortik/util/xml_etree.py
tortik-0.2.16.dist-info/LICENSE
tortik-0.2.16.dist-info/METADATA
tortik-0.2.16.dist-info/WHEEL
tortik-0.2.16.dist-info/top_level.txt
tortik-0.2.16.dist-info/RECORD
