Metadata-Version: 2.1
Name: tortik
Version: 0.2.16
Summary: Tortik - python tornado framework
Home-page: https://github.com/glibin/tortik
Download-URL: https://github.com/glibin/tortik/tarball/0.2.16
Classifier: License :: OSI Approved :: MIT License
Classifier: Programming Language :: Python
Classifier: Programming Language :: Python :: 2.7
Classifier: Programming Language :: Python :: 3.5
Classifier: Programming Language :: Python :: 3.7
License-File: LICENSE
Requires-Dist: tornado (<=5.1.1,>=5.0)
Requires-Dist: pycurl (>=7.19.0)
Requires-Dist: lxml (>=2.2.8)
Requires-Dist: jinja2 (<3,>2)
Requires-Dist: six
Requires-Dist: MarkupSafe (<2.1.0)
